PYBRDOC/__init__.py
PYBRDOC/cnpj.py
PYBRDOC/cpf.py
PYBRDOC/documentoidentificacao.py
PYBRDOC/inscricaoestadual.py
PYBRDOC/inscricaosuframa.py
PYBRDOC/validadoresie/__init__.py
PYBRDOC/validadoresie/validadorac.py
PYBRDOC/validadoresie/validadoral.py
PYBRDOC/validadoresie/validadoram.py
PYBRDOC/validadoresie/validadorap.py
PYBRDOC/validadoresie/validadorba.py
PYBRDOC/validadoresie/validadorce.py
PYBRDOC/validadoresie/validadordf.py
PYBRDOC/validadoresie/validadores.py
PYBRDOC/validadoresie/validadorgo.py
PYBRDOC/validadoresie/validadorma.py
PYBRDOC/validadoresie/validadormg.py
PYBRDOC/validadoresie/validadorms.py
PYBRDOC/validadoresie/validadormt.py
PYBRDOC/validadoresie/validadorpa.py
PYBRDOC/validadoresie/validadorpb.py
PYBRDOC/validadoresie/validadorpe.py
PYBRDOC/validadoresie/validadorpi.py
PYBRDOC/validadoresie/validadorpr.py
PYBRDOC/validadoresie/validadorrj.py
PYBRDOC/validadoresie/validadorrn.py
PYBRDOC/validadoresie/validadorro.py
PYBRDOC/validadoresie/validadorrr.py
PYBRDOC/validadoresie/validadorrs.py
PYBRDOC/validadoresie/validadorsc.py
PYBRDOC/validadoresie/validadorse.py
PYBRDOC/validadoresie/validadorsp.py
PYBRDOC/validadoresie/validadorto.py
DOCBRPY-0.1.3.dist-info/METADATA
DOCBRPY-0.1.3.dist-info/WHEEL
DOCBRPY-0.1.3.dist-info/top_level.txt
DOCBRPY-0.1.3.dist-info/RECORD
