Metadata-Version: 2.1
Name: DOCBRPY
Version: 0.1.3
Summary: Biblioteca para ajudar na validação de documentos em sistemas e verificação da sua existencia no banco de dados da Receita Federal
Home-page: 
Author: Heytor Norberth Leite da Silva
Author-email: heytornorberth2@gmail.com
License: MIT
Requires-Python: >=3.8
